MANIFEST.in
README.md
setup.py
django_mysql_fix/__init__.py
django_mysql_fix/version.py
django_mysql_fix.egg-info/PKG-INFO
django_mysql_fix.egg-info/SOURCES.txt
django_mysql_fix.egg-info/dependency_links.txt
django_mysql_fix.egg-info/requires.txt
django_mysql_fix.egg-info/top_level.txt
django_mysql_fix/backends/__init__.py
django_mysql_fix/backends/mysql/__init__.py
django_mysql_fix/backends/mysql/base.py
django_mysql_fix/backends/mysql/client.py
django_mysql_fix/backends/mysql/compiler.py
django_mysql_fix/backends/mysql/creation.py
django_mysql_fix/backends/mysql/introspection.py
django_mysql_fix/backends/mysql/schema.py
django_mysql_fix/backends/mysql/validation.py