Metadata-Version: 1.0
Name: django-mysql-fix
Version: 0.1.3
Summary: This project contains optimizations (hacks) for MySQL for Django ORM
Home-page: https://github.com/frol/django-mysql-fix
Author: Vladyslav Frolov
Author-email: frolvlad@gmail.com
License: UNKNOWN
Platform: UNKNOWN
